{
  "title": "The Greater Bengaluru Governance Act, 2024",
  "act_number": "Karnataka Act No. 36 of 2025",
  "pages": 166,
  "source": "Karnataka e-Gazette",
  "chapters": [
    {
      "number": "I",
      "title": "Preliminary",
      "page_start": 19,
      "page_end": 23,
      "sections": [
        {
          "number": "1",
          "title": "Short title, extent and commencement"
        },
        {
          "number": "2",
          "title": "Definitions"
        }
      ]
    },
    {
      "number": "II",
      "title": "Establishment of Civic Authorities in the Greater Bengaluru Area",
      "page_start": 24,
      "page_end": 26,
      "sections": [
        {
          "number": "3",
          "title": "Declaration of the Greater Bengaluru Area"
        },
        {
          "number": "4",
          "title": "Civic Authorities in the Greater Bengaluru Area"
        },
        {
          "number": "5",
          "title": "Establishment of City Corporations"
        },
        {
          "number": "6",
          "title": "Power to alter the boundaries of the City Corporations"
        },
        {
          "number": "7",
          "title": "Reconstitution of Bruhat Bengaluru Mahanagara Palike and other local authorities"
        },
        {
          "number": "8",
          "title": "Relationship between Civic Authorities in the Greater Bengaluru Area"
        }
      ]
    },
    {
      "number": "III",
      "title": "Greater Bengaluru Authority",
      "page_start": 26,
      "page_end": 35,
      "sections": [
        {
          "number": "9",
          "title": "Constitution of the Greater Bengaluru Authority"
        },
        {
          "number": "10",
          "title": "Chief Commissioner of Greater Bengaluru Authority"
        },
        {
          "number": "11",
          "title": "Officers of the Greater Bengaluru Authority"
        },
        {
          "number": "12",
          "title": "Meetings of the Greater Bengaluru Authority"
        },
        {
          "number": "13",
          "title": "Constitution of Executive Committee"
        },
        {
          "number": "14",
          "title": "Functions of the Greater Bengaluru Authority"
        },
        {
          "number": "15",
          "title": "Formulation and Execution of the major projects in the Greater Bengaluru Area"
        },
        {
          "number": "16",
          "title": "Economic Development Agency"
        },
        {
          "number": "17",
          "title": "Climate Action Cell"
        },
        {
          "number": "18",
          "title": "Sectoral Expert Committees"
        },
        {
          "number": "19",
          "title": "Power of supervision and to issue directions to authorities"
        },
        {
          "number": "20",
          "title": "Finances of Greater Bengaluru Authority"
        },
        {
          "number": "21",
          "title": "Budget"
        },
        {
          "number": "22",
          "title": "Annual Report"
        },
        {
          "number": "23",
          "title": "Power of Authority to borrow"
        },
        {
          "number": "24",
          "title": "Accounts and Audit"
        }
      ]
    },
    {
      "number": "IV",
      "title": "City Corporation Authorities",
      "page_start": 35,
      "page_end": 35,
      "sections": [
        {
          "number": "25",
          "title": "The Authorities of the City Corporation"
        }
      ]
    },
    {
      "number": "V",
      "title": "Constitution of the City Corporation",
      "page_start": 36,
      "page_end": 39,
      "sections": [
        {
          "number": "26",
          "title": "Establishment of City Corporations"
        },
        {
          "number": "27",
          "title": "Erection and maintenance of boundary marks"
        },
        {
          "number": "28",
          "title": "Duration of the City Corporations"
        },
        {
          "number": "29",
          "title": "Delimitation of Wards"
        },
        {
          "number": "30",
          "title": "Constitution of the City Corporation"
        },
        {
          "number": "31",
          "title": "Oath of allegiance to be taken by Councillors"
        },
        {
          "number": "32",
          "title": "Declaration of assets etc."
        },
        {
          "number": "33",
          "title": "Term of office of Councillors"
        }
      ]
    },
    {
      "number": "VI",
      "title": "Elections",
      "page_start": 39,
      "page_end": 54,
      "sections": [
        {
          "number": "34",
          "title": "Election to the City Corporation"
        },
        {
          "number": "35",
          "title": "Electoral rolls"
        },
        {
          "number": "36",
          "title": "Electoral Registration Officer"
        },
        {
          "number": "37",
          "title": "Provision of polling stations"
        },
        {
          "number": "38",
          "title": "Appointment of Presiding Officers for polling stations"
        },
        {
          "number": "39",
          "title": "Qualifications for being a Councillor"
        },
        {
          "number": "40",
          "title": "Disqualifications of being a Councillor"
        },
        {
          "number": "41",
          "title": "Equality of votes"
        },
        {
          "number": "42",
          "title": "Publication of results"
        },
        {
          "number": "43",
          "title": "Election Petition"
        },
        {
          "number": "44",
          "title": "Grounds for declaring elections to be void"
        },
        {
          "number": "45",
          "title": "Procedure to be followed by the Court"
        },
        {
          "number": "46",
          "title": "Decision of the Court"
        },
        {
          "number": "47",
          "title": "Appeal"
        },
        {
          "number": "48",
          "title": "Corrupt Practices"
        },
        {
          "number": "49",
          "title": "Promoting enmity between classes in connection with election"
        },
        {
          "number": "50",
          "title": "Prohibition of public meetings two days before preceding the election day and on the election day"
        },
        {
          "number": "51",
          "title": "Disturbances at election meetings"
        },
        {
          "number": "52",
          "title": "Restrictions on the printing of pamphlets, poster and others"
        },
        {
          "number": "53",
          "title": "Maintenance of secrecy of voting"
        },
        {
          "number": "54",
          "title": "Prohibition of canvassing in or near polling stations"
        },
        {
          "number": "55",
          "title": "Penalty for disorderly conduct in or near polling stations"
        },
        {
          "number": "56",
          "title": "Penalty for illegal hiring or procuring of conveyances at elections"
        },
        {
          "number": "57",
          "title": "Breaches of official duty in connection with elections"
        },
        {
          "number": "58",
          "title": "Returning Officer, Presiding Officer, etc. deemed to be on deputation to State Election Commission"
        },
        {
          "number": "59",
          "title": "Penalty for Government servant for acting as election agent, polling agent or counting agent"
        },
        {
          "number": "60",
          "title": "Removal of electronic voting machine from polling station to be an offence"
        },
        {
          "number": "61",
          "title": "Other offences and penalties therefor"
        },
        {
          "number": "62",
          "title": "Prosecution regarding certain offences"
        },
        {
          "number": "63",
          "title": "Right to vote"
        },
        {
          "number": "64",
          "title": "Account of election expenses and maximum thereof"
        },
        {
          "number": "65",
          "title": "Lodging of account with the returning officer"
        },
        {
          "number": "66",
          "title": "Failure to lodge an account of election expenses"
        },
        {
          "number": "67",
          "title": "Voting machines at elections"
        },
        {
          "number": "68",
          "title": "Power of Government to make rules for the purpose of election"
        },
        {
          "number": "69",
          "title": "Prohibition of simultaneous membership"
        },
        {
          "number": "70",
          "title": "Requisitioning of premises, vehicle, etc., for election purpose"
        },
        {
          "number": "71",
          "title": "Payment of compensation"
        },
        {
          "number": "72",
          "title": "Power to obtain information"
        },
        {
          "number": "73",
          "title": "Power of entry into and inspection of premises, etc."
        },
        {
          "number": "74",
          "title": "Eviction from requisitioned premises"
        },
        {
          "number": "75",
          "title": "Release of premises from requisitioning"
        },
        {
          "number": "76",
          "title": "Penalty for contravention of any order regarding requisition"
        }
      ]
    },
    {
      "number": "VII",
      "title": "Mayor, Deputy Mayor, Commissioner, Standing Committee, Ward Committee",
      "page_start": 54,
      "page_end": 63,
      "sections": [
        {
          "number": "77",
          "title": "Mayor and Deputy Mayor"
        },
        {
          "number": "78",
          "title": "Term of office of the Mayor and Deputy Mayor"
        },
        {
          "number": "79",
          "title": "Reservation of the office of the Mayor and Deputy Mayor"
        },
        {
          "number": "80",
          "title": "Powers and functions of the Mayor"
        },
        {
          "number": "81",
          "title": "Functions of the Deputy Mayor"
        },
        {
          "number": "82",
          "title": "Resignation of Mayor and Deputy Mayor"
        },
        {
          "number": "83",
          "title": "Honoraria, fees or allowances"
        },
        {
          "number": "84",
          "title": "Commissioner"
        },
        {
          "number": "85",
          "title": "Powers and Functions of the Commissioner"
        },
        {
          "number": "86",
          "title": "Commissioner to carry on correspondence"
        },
        {
          "number": "87",
          "title": "Delegation of Commissioner powers"
        },
        {
          "number": "88",
          "title": "Custody of records"
        },
        {
          "number": "89",
          "title": "Control over City Corporation establishment"
        },
        {
          "number": "90",
          "title": "Salary and Allowances of the Commissioner"
        },
        {
          "number": "91",
          "title": "Appointment of officiating Commissioner in case of death, resignation or removal of Commissioner"
        },
        {
          "number": "92",
          "title": "Joint Commissioner of a Zone"
        },
        {
          "number": "93",
          "title": "Salary and Conditions of service of the Joint Commissioner"
        },
        {
          "number": "94",
          "title": "Powers and Functions of the Joint Commissioner"
        },
        {
          "number": "95",
          "title": "Assembly Constituency Level Consultative and Co-ordination Committee"
        },
        {
          "number": "96",
          "title": "Functions of Assembly Constituency Level Consultative and Co-ordination Committee"
        },
        {
          "number": "97",
          "title": "Allocation of Funds"
        },
        {
          "number": "98",
          "title": "Establishment of Standing Committees"
        },
        {
          "number": "99",
          "title": "Powers and Functions of the Standing Committee"
        },
        {
          "number": "100",
          "title": "Constitution and Composition of the Ward Committee"
        },
        {
          "number": "101",
          "title": "Procedure for nomination as a member of the Ward Committee"
        },
        {
          "number": "102",
          "title": "Meeting of the Ward Committee"
        },
        {
          "number": "103",
          "title": "Functions of the Ward Committee"
        },
        {
          "number": "104",
          "title": "Power of Councillors"
        },
        {
          "number": "105",
          "title": "Appeal to the Election of Mayor, Deputy Mayor etc."
        }
      ]
    },
    {
      "number": "VIII",
      "title": "City Corporation Officers and Servants and their Appointments and Conditions of Service",
      "page_start": 63,
      "page_end": 65,
      "sections": [
        {
          "number": "106",
          "title": "Appointment to certain posts under the City Corporations to be made from Karnataka Municipal Administrative Service"
        },
        {
          "number": "107",
          "title": "Appointment of Engineer, Town Planner, Health Officer, Accounts Officer etc."
        },
        {
          "number": "108",
          "title": "Legal cell"
        },
        {
          "number": "109",
          "title": "Contribution in respect of Government servants"
        }
      ]
    },
    {
      "number": "IX",
      "title": "Powers, Functions and Procedures of the City Corporation and Committees",
      "page_start": 65,
      "page_end": 68,
      "sections": [
        {
          "number": "110",
          "title": "General powers of the City Corporation"
        },
        {
          "number": "111",
          "title": "Powers and Functions of the City Corporation"
        },
        {
          "number": "112",
          "title": "Additional Functions assigned by the Government"
        },
        {
          "number": "113",
          "title": "First charge on City Corporation Fund"
        },
        {
          "number": "114",
          "title": "Proceedings of the City Corporation and Standing Committees"
        },
        {
          "number": "115",
          "title": "Obligation on remaining City Corporation authorities to carry out resolutions of the City Corporation"
        },
        {
          "number": "116",
          "title": "The City Corporation may call for extracts from proceedings, etc., from the Standing Committee, etc."
        },
        {
          "number": "117",
          "title": "Proceedings of the City Corporation, etc."
        },
        {
          "number": "118",
          "title": "Record of proceedings"
        },
        {
          "number": "119",
          "title": "Proceedings of meetings to be good and valid until contrary is proved"
        },
        {
          "number": "120",
          "title": "The Commissioner's right to attend and take part in discussion but not to move resolution or to vote"
        },
        {
          "number": "121",
          "title": "The Councillors to refrain from taking part in discussion and voting on questions in which they have pecuniary interest"
        },
        {
          "number": "122",
          "title": "Submission of administration report"
        }
      ]
    },
    {
      "number": "X",
      "title": "Essential Services",
      "page_start": 68,
      "page_end": 69,
      "sections": [
        {
          "number": "123",
          "title": "Declaration of Essential Services, etc."
        },
        {
          "number": "124",
          "title": "Power of the Government and the Greater Bengaluru Authority to declare emergency"
        }
      ]
    },
    {
      "number": "XI",
      "title": "Power of the Government",
      "page_start": 69,
      "page_end": 73,
      "sections": [
        {
          "number": "125",
          "title": "Power of the Government to call for records and to cause inspection to be made"
        },
        {
          "number": "126",
          "title": "Power of the Government to take action in respect of matters pending un-disposed of before the City Corporation"
        },
        {
          "number": "127",
          "title": "The Government power to direct the taking of action"
        },
        {
          "number": "128",
          "title": "Power to appoint an officer to take action in default, at the expense of the City Corporation"
        },
        {
          "number": "129",
          "title": "Power to cancel resolution and orders"
        },
        {
          "number": "130",
          "title": "Power of the Government to dissolve the City Corporation"
        },
        {
          "number": "131",
          "title": "Appointment of City Corporation Administrator"
        },
        {
          "number": "132",
          "title": "Establishment of performance management system"
        }
      ]
    },
    {
      "number": "XII",
      "title": "Property of the City Corporation",
      "page_start": 73,
      "page_end": 76,
      "sections": [
        {
          "number": "133",
          "title": "Property of the City Corporation"
        },
        {
          "number": "134",
          "title": "Disposal of property by the City Corporation"
        },
        {
          "number": "135",
          "title": "Acquisition of the property by the City Corporation"
        },
        {
          "number": "136",
          "title": "Property of the Government managed by the City Corporation"
        },
        {
          "number": "137",
          "title": "Power of the Government to manage the City Corporation property"
        },
        {
          "number": "138",
          "title": "Decision of claims to the property by or against the City Corporation"
        },
        {
          "number": "139",
          "title": "Power of the City Corporation to manage private property"
        },
        {
          "number": "140",
          "title": "Maintenance of Property register"
        },
        {
          "number": "141",
          "title": "Objects not provided for by this Act"
        }
      ]
    },
    {
      "number": "XIII",
      "title": "Contracts",
      "page_start": 76,
      "page_end": 77,
      "sections": [
        {
          "number": 142,
          "title": "Power of the City Corporation to enter into contracts"
        },
        {
          "number": 143,
          "title": "Invitation of tenders"
        },
        {
          "number": 144,
          "title": "Maintenance of database"
        }
      ]
    },
    {
      "number": "XIV",
      "title": "Taxation and Finance",
      "page_start": 77,
      "page_end": 92,
      "sections": [
        {
          "number": 145,
          "title": "Revenues of the City Corporation"
        },
        {
          "number": 146,
          "title": "Power to levy taxes, cesses, duties and service charges"
        },
        {
          "number": 147,
          "title": "Levy of property tax"
        },
        {
          "number": 148,
          "title": "Payment of Property Tax"
        },
        {
          "number": 149,
          "title": "Obligation of transferor and transferee to give notice of transfer"
        },
        {
          "number": 150,
          "title": "Scrutiny of tax return"
        },
        {
          "number": 151,
          "title": "Limitation period for assessment of property tax"
        },
        {
          "number": 152,
          "title": "Revision of Property Tax"
        },
        {
          "number": 153,
          "title": "Power to suspend, reduce or abolish any existing tax"
        },
        {
          "number": 154,
          "title": "General exemptions"
        },
        {
          "number": 155,
          "title": "Property tax a first charge on property and movables"
        },
        {
          "number": 156,
          "title": "Property tax from whom and when payable"
        },
        {
          "number": 157,
          "title": "Preparation and publication of property tax register"
        },
        {
          "number": 158,
          "title": "Survey of lands and buildings and preparation of property tax register"
        },
        {
          "number": 159,
          "title": "Demand for payment of property tax and appeal against such demand"
        },
        {
          "number": 160,
          "title": "Fee on advertisement"
        },
        {
          "number": 161,
          "title": "Prohibition of advertisements without permission of the Commissioner"
        },
        {
          "number": 162,
          "title": "Permission of the Commissioner to become void in certain cases"
        },
        {
          "number": 163,
          "title": "Removal and Demolition of unauthorised advertisement"
        },
        {
          "number": 164,
          "title": "Cesses that may be imposed"
        },
        {
          "number": 165,
          "title": "Power to levy user charges"
        },
        {
          "number": 166,
          "title": "Levy of entertainment tax"
        },
        {
          "number": 167,
          "title": "Power to levy fees and fines"
        },
        {
          "number": 168,
          "title": "Power to levy development charges"
        },
        {
          "number": 169,
          "title": "Levy of surcharge on tax or fee"
        },
        {
          "number": 170,
          "title": "Duty on transfer of immovable properties"
        },
        {
          "number": 171,
          "title": "Power to effect recovery of the taxes, fees, cesses, interest, penalties etc."
        },
        {
          "number": 172,
          "title": "Exclusive Jurisdiction of the Chief Commissioner, Greater Bengaluru Authority, Commissioners of the City Corporations and the Authorized Officers and bar of jurisdiction of Civil Courts"
        },
        {
          "number": 173,
          "title": "Savings of certain suits"
        },
        {
          "number": 174,
          "title": "Plaintiff to exhaust his right of appeal before instituting a suit or other proceeding against the Greater Bengaluru Authority and the City Corporations"
        },
        {
          "number": 175,
          "title": "Power of Civil Court to refer questions of jurisdiction to High Court"
        }
      ]
    },
    {
      "number": "XV",
      "title": "City Corporation Fund, Budget, Accounts and Audit",
      "page_start": 92,
      "page_end": 99,
      "sections": [
        {
          "number": 176,
          "title": "The City Corporation Fund"
        },
        {
          "number": 177,
          "title": "Application of the City Corporation Fund"
        },
        {
          "number": 178,
          "title": "Urban Transport Fund"
        },
        {
          "number": 179,
          "title": "Contribution to expenditure by the City Corporation"
        },
        {
          "number": 180,
          "title": "Attachment of City Corporation fund for recovery of money borrowed from the Government"
        },
        {
          "number": 181,
          "title": "Preparation of the City Corporation budget"
        },
        {
          "number": 182,
          "title": "Budget estimates to be prepared by the Standing Committee for taxation, finance and appeals"
        },
        {
          "number": 183,
          "title": "Power of City Corporation to alter budget grant"
        },
        {
          "number": 184,
          "title": "Obligation to pass budget before the beginning of the year"
        },
        {
          "number": 185,
          "title": "City Corporation may pass supplemental budget"
        },
        {
          "number": 186,
          "title": "Re-adjustment of income and expenditure to be made by the City Corporation during the course of the official year whenever necessary"
        },
        {
          "number": 187,
          "title": "Preparation of a medium-term fiscal plan"
        },
        {
          "number": 188,
          "title": "Comprehensive Debt Limitation Policy"
        },
        {
          "number": 189,
          "title": "Mandatory compliance"
        },
        {
          "number": 190,
          "title": "Establishment of Sinking Fund"
        },
        {
          "number": 191,
          "title": "Investment of amount at the credit of the Sinking Fund"
        },
        {
          "number": 192,
          "title": "Application of the sinking fund"
        },
        {
          "number": 193,
          "title": "Annual statement by the City Corporation"
        },
        {
          "number": 194,
          "title": "Appointment of the Chief Financial Officer"
        },
        {
          "number": 195,
          "title": "Annual Financial statement"
        },
        {
          "number": 196,
          "title": "Accounts and Audit"
        }
      ]
    },
    {
      "number": "XVI",
      "title": "Public Streets",
      "page_start": 99,
      "page_end": 108,
      "sections": [
        {
          "number": 197,
          "title": "Vesting of Public streets in the City Corporation and their appurtenances"
        },
        {
          "number": 198,
          "title": "Powers of the Commissioner in respect of public streets"
        },
        {
          "number": 199,
          "title": "Powers of the Chief Commissioner in respect of public streets overlapping two or more City Corporations"
        },
        {
          "number": 200,
          "title": "Power to make new public streets"
        },
        {
          "number": 201,
          "title": "Minimum width of new public streets"
        },
        {
          "number": 202,
          "title": "Power to prohibit use of public streets for certain kind of traffic and on street parking"
        },
        {
          "number": 203,
          "title": "Khatadar's obligation when dealing with land as building sites"
        },
        {
          "number": 204,
          "title": "Making of new private streets"
        },
        {
          "number": 205,
          "title": "Alteration or demolition of street made in breach of this Act"
        },
        {
          "number": 206,
          "title": "Utilisation of permanently closed streets"
        },
        {
          "number": 207,
          "title": "Acquisition of land and buildings for improvement of streets"
        },
        {
          "number": 208,
          "title": "Powers to prescribe building line and street alignment"
        },
        {
          "number": 209,
          "title": "Restriction on erection of or addition to buildings within street alignment or building line"
        },
        {
          "number": 210,
          "title": "Setting back projecting building or wall"
        },
        {
          "number": 211,
          "title": "Additional power of the Commissioner to order settling back of buildings to regular line of street"
        },
        {
          "number": 212,
          "title": "Power to declare any street as public street"
        },
        {
          "number": 213,
          "title": "Power of the Commissioner to Order work to be carried or carried out himself in default"
        },
        {
          "number": 214,
          "title": "Prohibition of projections upon streets"
        },
        {
          "number": 215,
          "title": "Prohibition of structures or fixtures which cause obstruction in streets"
        },
        {
          "number": 216,
          "title": "Removal of encroachments"
        },
        {
          "number": 217,
          "title": "Precautions during repair of streets"
        },
        {
          "number": 218,
          "title": "Streets not to be opened or broken up and building materials not to be deposited thereon without permission"
        },
        {
          "number": 219,
          "title": "Naming and numbering"
        },
        {
          "number": 220,
          "title": "Provision for lighting of Public Streets"
        },
        {
          "number": 221,
          "title": "Prohibition of removal of street lights"
        },
        {
          "number": 222,
          "title": "Power to allow certain erections"
        }
      ]
    },
    {
      "number": "XVII",
      "title": "Regulation of Buildings",
      "page_start": 108,
      "page_end": 123,
      "sections": [
        {
          "number": 223,
          "title": "Exercise of powers by a Corporation to be in conformity with the provisions of the Karnataka Town and Country Planning Act, 1961"
        },
        {
          "number": 224,
          "title": "Building bye-laws"
        },
        {
          "number": 225,
          "title": "Obligation to provide for rain water harvesting structure"
        },
        {
          "number": 226,
          "title": "Relinquishment of area reserved for road"
        },
        {
          "number": 227,
          "title": "Building at corner of streets"
        },
        {
          "number": 228,
          "title": "Prohibition of construction without sanction"
        },
        {
          "number": 229,
          "title": "Application to construct or re-construct building"
        },
        {
          "number": 230,
          "title": "Procedure for grant of sanction to building plan"
        },
        {
          "number": 231,
          "title": "Period within which the Commissioner to grant or refuse to grant permission to execute work"
        },
        {
          "number": 232,
          "title": "Power of the Corporation to fix rate of fee to be levied for issue of permission under this chapter"
        },
        {
          "number": 233,
          "title": "Levy of imposts, restriction and condition by the Commissioner"
        },
        {
          "number": 234,
          "title": "Exemptions for Levy of imposts, restriction and conditions"
        },
        {
          "number": 235,
          "title": "Power of the Government to exempt or reduce fee levied or charged or assessed"
        },
        {
          "number": 236,
          "title": "Grounds on which approval of site for, or permission to construct building, shall be refused"
        },
        {
          "number": 237,
          "title": "Issue of Modified license and extension of license period"
        },
        {
          "number": 238,
          "title": "Restriction on the power to sanction construction of a place of entertainment in certain cases"
        },
        {
          "number": 239,
          "title": "Building construction shall not be proceeded without plinth certificate"
        },
        {
          "number": 240,
          "title": "Power of Commissioner to require alteration of work"
        },
        {
          "number": 241,
          "title": "Grant of Occupancy certificate"
        },
        {
          "number": 242,
          "title": "Application of provisions to additions and alterations"
        },
        {
          "number": 243,
          "title": "Demolition or alteration of buildings unlawfully commenced, continued or completed"
        },
        {
          "number": 244,
          "title": "Power to enforce demolition order in default"
        },
        {
          "number": 245,
          "title": "Power of the Commissioner to suspend or revoke permission"
        },
        {
          "number": 246,
          "title": "Compliance by the khatadar or person responsible and the utility service providers for ensuring construction or occupancy to be in conformity with permissions accorded"
        },
        {
          "number": 247,
          "title": "Penalty against jurisdictional officer delegated by the Commissioner for failing to prevent un-authorized deviations or constructions"
        },
        {
          "number": 248,
          "title": "Power of the Government to regulate future construction of certain classes of buildings in particular streets or localities"
        },
        {
          "number": 249,
          "title": "Regularisation of certain unlawful buildings"
        },
        {
          "number": 250,
          "title": "Appeal against the decisions of the Commissioner"
        }
      ]
    },
    {
      "number": "XVIII",
      "title": "Public Health",
      "page_start": 123,
      "page_end": 128,
      "sections": [
        {
          "number": 251,
          "title": "Duties of the City Corporation with respect to public health"
        },
        {
          "number": 252,
          "title": "City Corporation's power to order or undertake the inspection or sanitation of buildings or sites"
        },
        {
          "number": 253,
          "title": "Power to notify dangerous and communicable diseases"
        },
        {
          "number": 254,
          "title": "Disinfection of buildings and articles"
        },
        {
          "number": 255,
          "title": "Provision of places for disinfection and power to destroy infected articles"
        },
        {
          "number": 256,
          "title": "Power to order closure of places of public purposes or entertainment"
        },
        {
          "number": 257,
          "title": "Prohibition against transfer of infected articles"
        },
        {
          "number": 258,
          "title": "Prohibition against infected person carrying on occupation"
        },
        {
          "number": 259,
          "title": "Prohibition against diseased person entering public conveyance"
        },
        {
          "number": 260,
          "title": "Disinfection of public conveyance after carriage of patients"
        },
        {
          "number": 261,
          "title": "Letting of infected building"
        },
        {
          "number": 262,
          "title": "Minor suffering from dangerous and communicable disease not to attend school"
        },
        {
          "number": 263,
          "title": "Provision as to library books"
        },
        {
          "number": 264,
          "title": "Power to prohibit use of water likely to spread infection"
        },
        {
          "number": 265,
          "title": "Compulsory vaccination"
        },
        {
          "number": 266,
          "title": "Obligation to give information of dangerous and communicable disease"
        },
        {
          "number": 267,
          "title": "Prohibition to enter the City"
        },
        {
          "number": 268,
          "title": "Power to stop dangerous quarrying"
        },
        {
          "number": 269,
          "title": "Power to order filling in pools, etc., which are a nuisance and regulation of agriculture within the City"
        }
      ]
    },
    {
      "number": "XIX",
      "title": "Urban Disaster Management",
      "page_start": 128,
      "page_end": 128,
      "sections": [
        {
          "number": 270,
          "title": "Management of disasters"
        }
      ]
    },
    {
      "number": "XX",
      "title": "Solid Waste Management",
      "page_start": 128,
      "page_end": 132,
      "sections": [
        {
          "number": 271,
          "title": "Duty of the City Corporation and the Commissioner in handling solid waste"
        },
        {
          "number": 272,
          "title": "Entrustment of management and handling of solid wastes and billing and collection of charges"
        },
        {
          "number": 273,
          "title": "Identification of places for disposal and final disposal of solid waste"
        },
        {
          "number": 274,
          "title": "Duty of khatadars and occupiers of premises to store solid wastes at the source of the generation"
        },
        {
          "number": 275,
          "title": "Duty of the City Corporation for handling different types of waste"
        },
        {
          "number": 276,
          "title": "Responsibilities of commercial waste generators"
        },
        {
          "number": 277,
          "title": "Functions of the Ward Committee"
        },
        {
          "number": 278,
          "title": "Duties of Ward Committees with regards to waste management"
        },
        {
          "number": 279,
          "title": "Ward Micro Plan"
        },
        {
          "number": 280,
          "title": "Training and public awareness"
        },
        {
          "number": 281,
          "title": "Reduction of waste by the City Corporation"
        },
        {
          "number": 282,
          "title": "Penalties for contravention of waste management"
        },
        {
          "number": 283,
          "title": "Waste generated during public gatherings"
        }
      ]
    },
    {
      "number": "XXI",
      "title": "Nuisances",
      "page_start": 132,
      "page_end": 136,
      "sections": [
        {
          "number": 284,
          "title": "Prohibition of nuisance"
        },
        {
          "number": 285,
          "title": "Control of pollution and polluter pays principle"
        },
        {
          "number": 286,
          "title": "Precautions in case of dangerous structures"
        },
        {
          "number": 287,
          "title": "Precautions in case of dangerous trees"
        },
        {
          "number": 288,
          "title": "Precautions in case of dangerous tanks, wells, holes etc."
        },
        {
          "number": 289,
          "title": "Precautions against fire"
        },
        {
          "number": 290,
          "title": "Removal of filth or noxious vegetation"
        },
        {
          "number": 291,
          "title": "Abatement of nuisance from dust, smoke, etc."
        },
        {
          "number": 292,
          "title": "Fencing of buildings or lands and pruning of hedges and trees"
        },
        {
          "number": 293,
          "title": "Building unfit for human habitation"
        },
        {
          "number": 294,
          "title": "Khatadar undertakes to execute the works necessary"
        },
        {
          "number": 295,
          "title": "Bar to claim compensation"
        }
      ]
    },
    {
      "number": "XXII",
      "title": "Urban Heritage",
      "page_start": 136,
      "page_end": 139,
      "sections": [
        {
          "number": 296,
          "title": "Protection, Conservation and Maintenance of Urban Heritage"
        },
        {
          "number": 297,
          "title": "Preparation of List of Heritage Sites Including Heritage Buildings, Heritage Precincts and Listed Natural Features Areas"
        },
        {
          "number": 298,
          "title": "Incentives for Heritage Buildings"
        },
        {
          "number": 299,
          "title": "Constitution of Heritage Conservation Committee"
        },
        {
          "number": 300,
          "title": "Grading of Heritage Buildings and Sites"
        },
        {
          "number": 301,
          "title": "Functions of the Heritage Conservation Committee"
        },
        {
          "number": 302,
          "title": "Ownership not affected"
        }
      ]
    },
    {
      "number": "XXIII",
      "title": "Licences and Permissions",
      "page_start": 139,
      "page_end": 142,
      "sections": [
        {
          "number": 303,
          "title": "Granting of license"
        },
        {
          "number": 304,
          "title": "Exemption of the Government from procuring license"
        },
        {
          "number": 305,
          "title": "Licenses and written permission to specify conditions on which they are granted"
        },
        {
          "number": 306,
          "title": "Power of the Commissioner to stop use of premises used in contravention of licenses"
        },
        {
          "number": 307,
          "title": "Inspection of places where sale is carried out"
        },
        {
          "number": 308,
          "title": "Power of the Commissioner for the purposes of inspection"
        },
        {
          "number": 309,
          "title": "Appeal to the Chief Commissioner"
        },
        {
          "number": 310,
          "title": "Period of limitation for appeals"
        },
        {
          "number": 311,
          "title": "Summons to attend and give evidence or produce documents"
        },
        {
          "number": 312,
          "title": "Consequences of failure to obtain licences, etc., or breach of the same"
        },
        {
          "number": 313,
          "title": "Recovery of expenses from persons liable and limitation or liability of occupier"
        }
      ]
    },
    {
      "number": "XXIV",
      "title": "Rules, Regulations and Bye-laws",
      "page_start": 142,
      "page_end": 148,
      "sections": [
        {
          "number": 314,
          "title": "Power of the State Government to make rules and orders"
        },
        {
          "number": 315,
          "title": "Power of the Greater Bengaluru Authority to make regulations"
        },
        {
          "number": 316,
          "title": "Power of Greater Bengaluru Authority to make model bye-laws and adoption of such bye-laws by City Corporations"
        },
        {
          "number": 317,
          "title": "Additional Power of City Corporation to make Bye-laws"
        },
        {
          "number": 318,
          "title": "Power of City Corporation to make regulations"
        }
      ]
    },
    {
      "number": "XXV",
      "title": "Penalties",
      "page_start": 148,
      "page_end": 149,
      "sections": [
        {
          "number": 319,
          "title": "Penalty for violation of the provisions of the Act"
        },
        {
          "number": 320,
          "title": "Penalty for violation of the rules"
        },
        {
          "number": 321,
          "title": "Penalty for violation of the regulations"
        },
        {
          "number": 322,
          "title": "Penalty for violation of the bye-laws"
        },
        {
          "number": 323,
          "title": "Penalty for un-authorised use of the Corporation property"
        },
        {
          "number": 324,
          "title": "Penalty for leaving vehicle or animal in dangerous position in public street"
        },
        {
          "number": 325,
          "title": "Compounding of offence"
        },
        {
          "number": 326,
          "title": "Power to give retrospective effect to certain bye-laws and penalties for breaches of bye-laws"
        }
      ]
    },
    {
      "number": "XXVI",
      "title": "Miscellaneous",
      "page_start": 149,
      "page_end": 158,
      "sections": [
        {
          "number": 327,
          "title": "Indemnity to Government, City Corporation authorities, officers and servants"
        },
        {
          "number": 328,
          "title": "Sanction for prosecution of Mayor, Deputy Mayor, etc."
        },
        {
          "number": 329,
          "title": "Assessment, etc., not to be impeached"
        },
        {
          "number": 330,
          "title": "Duties of police officers"
        },
        {
          "number": 331,
          "title": "Power of police officer to arrest persons"
        },
        {
          "number": 332,
          "title": "Exercise of powers of police officer by the Bengaluru Metropolitan Task Force or City Corporation servants"
        },
        {
          "number": 333,
          "title": "Prohibition against obstruction of proceedings of City Corporation, Standing Committee, Mayor, etc."
        },
        {
          "number": 334,
          "title": "Prohibition against removal of mark"
        },
        {
          "number": 335,
          "title": "Liability of Commissioner of the City Corporation and Councillor for loss, waste or misapplication of fund, etc."
        },
        {
          "number": 336,
          "title": "Prohibition against removal or obliteration of notice"
        },
        {
          "number": 337,
          "title": "Prohibition against unauthorised dealings with public place or materials"
        },
        {
          "number": 338,
          "title": "Form of notices and permissions"
        },
        {
          "number": 339,
          "title": "Proof of consent of the Authority, City Corporation authorities or the officers"
        },
        {
          "number": 340,
          "title": "Signatures on documents"
        },
        {
          "number": 341,
          "title": "Publication of notification"
        },
        {
          "number": 342,
          "title": "Publication of order, notice or other documents"
        },
        {
          "number": 343,
          "title": "Publication in newspapers"
        },
        {
          "number": 344,
          "title": "Notice of prohibition or setting apart of places"
        },
        {
          "number": 345,
          "title": "Method of serving documents or notices"
        },
        {
          "number": 346,
          "title": "Recovery by occupier of sum leviable from khatadars"
        },
        {
          "number": 347,
          "title": "Obstruction of khatadar by occupier"
        },
        {
          "number": 348,
          "title": "Execution of work by occupier in default of khatadar"
        },
        {
          "number": 349,
          "title": "Time for complying with order and power to enforce in default"
        },
        {
          "number": 350,
          "title": "Power of the Commissioner to agree to receive payment of expenses in instalments"
        },
        {
          "number": 351,
          "title": "Power to declare expenses on certain works as improvement expenses"
        },
        {
          "number": 352,
          "title": "Improvement expenses by whom payable"
        },
        {
          "number": 353,
          "title": "Redemption of charge for improvement expenses"
        },
        {
          "number": 354,
          "title": "Application of term 'public servant' to the Greater Bengaluru Authority and the City Corporation officers, agents and sub-agents"
        },
        {
          "number": 355,
          "title": "Offences by companies and others"
        },
        {
          "number": 356,
          "title": "Official display of flag"
        },
        {
          "number": 357,
          "title": "Bidding prohibited"
        },
        {
          "number": 358,
          "title": "Effect of absorption of Panchayat area into a City Corporation area"
        },
        {
          "number": 359,
          "title": "Removal of difficulties"
        },
        {
          "number": 360,
          "title": "Transitory Provisions"
        },
        {
          "number": 361,
          "title": "Repeal and Savings"
        }
      ]
    }
  ],
  "schedules": {
    "I": {
      "title": "Functions of City Corporations",
      "section_reference": "111",
      "core_functions": [
        {
          "number": "i",
          "text": "Urban planning including town planning"
        },
        {
          "number": "ii",
          "text": "Regulation of land-use including protection of public land from encroachment and construction of buildings"
        },
        {
          "number": "iii",
          "text": "Planning for economic and social development"
        },
        {
          "number": "iv",
          "text": "Roads including flyover, underpass, subway, traffic islands, footpath road crossing facility, skywalk and bridges"
        },
        {
          "number": "v",
          "text": "Water supply for domestic, industrial and commercial purposes"
        },
        {
          "number": "vi",
          "text": "Public health, sanitation including storm water drains, conservancy and solid and liquid waste management"
        },
        {
          "number": "vii",
          "text": "Fire services"
        },
        {
          "number": "viii",
          "text": "Urban forestry, protection of the environment, promotion of ecological aspects and maintenance of environmental hygiene"
        },
        {
          "number": "ix",
          "text": "Safe guarding the interests of persons with physical and mental disabilities"
        },
        {
          "number": "x",
          "text": "Slum improvement and upgradation including providing basic facilities"
        },
        {
          "number": "xi",
          "text": "Urban poverty alleviation"
        },
        {
          "number": "xii",
          "text": "Provision and maintenance of urban amenities and facilities such as parks, gardens, playgrounds, public markets, bathing and washing ghats, waiting sheds for travelers"
        },
        {
          "number": "xiii",
          "text": "Promotion of cultural, educational and aesthetic aspects"
        },
        {
          "number": "xiv",
          "text": "Establishment and maintenance of burial and burning grounds, cremations, cremation grounds and electric crematoriums"
        },
        {
          "number": "xv",
          "text": "Cattle pounds, care and veterinary services including prevention of cruelty to animals"
        },
        {
          "number": "xvi",
          "text": "Collection and updating of vital statistics including registration of births, deaths and marriages"
        },
        {
          "number": "xvii",
          "text": "Provision and maintenance of public amenities including street lighting, parking spaces for vehicles, bus stops and public conveniences like toilet facilities at public places"
        },
        {
          "number": "xviii",
          "text": "Regulation of slaughter houses and tanneries and sale of meat, fish and other perishable food stuffs among others"
        }
      ],
      "general_functions": [
        {
          "number": "i",
          "text": "Organising voluntary workers and promote community participation in all development activities"
        },
        {
          "number": "ii",
          "text": "Organise campaign for thrift"
        },
        {
          "number": "iii",
          "text": "Awareness building against social evils such as dowry, domestic violence, abuse of children, casteism, homophobia, and xenophobia"
        },
        {
          "number": "iv",
          "text": "Organize legal awareness campaigns among weaker sections, campaign against economic offences, adherence to civic duties, and promoting communal harmony"
        },
        {
          "number": "v",
          "text": "Organise relief activities during natural calamities and maintain relief centres like hospitals, dispensaries, asylums, rescue homes, maternity houses and child welfare centres, etc."
        },
        {
          "number": "vi",
          "text": "Mobilising local resources in cash or in kind"
        },
        {
          "number": "vii",
          "text": "Organise and promote resident welfare associations, neighbourhood groups and committees, and self-help groups with focus on the poor"
        },
        {
          "number": "viii",
          "text": "Disclosure and dissemination of information of public interest"
        },
        {
          "number": "ix",
          "text": "Maintenance of public properties"
        },
        {
          "number": "x",
          "text": "Issue of licence to dangerous and offensive trades and industries"
        },
        {
          "number": "xi",
          "text": "Issue of licence to domestic pet animals"
        },
        {
          "number": "xii",
          "text": "Conservation and preservation of water bodies, gardens and green spaces"
        },
        {
          "number": "xiii",
          "text": "Conservation and preservation of places and buildings of historical and cultural importance"
        },
        {
          "number": "xiv",
          "text": "Promoting energy efficiency and build awareness on climate change"
        },
        {
          "number": "xv",
          "text": "Promote introduction of Information Technology and e-Governance in the working of the City Corporation"
        }
      ],
      "sector_functions": [
        {
          "number": "i",
          "title": "Urban Planning including Town Planning",
          "items": [
            {
              "sub": "a",
              "text": "Planned development of new areas for human settlement, erection and maintenance of boundary marks defining the limits or any alteration in the limits"
            },
            {
              "sub": "b",
              "text": "Measures for beautification of the City Corporation area by setting up fountains, providing recreational areas, improving river banks, and landscaping"
            },
            {
              "sub": "c",
              "text": "Integration of the development plans and schemes of the municipal area with the district or regional development plan"
            },
            {
              "sub": "d",
              "text": "Preparation and keeping up to date of appropriate maps, data and records of lands within City Corporation and utility to which such lands are from time to time put"
            }
          ]
        },
        {
          "number": "ii",
          "title": "Environment and Social Forestry",
          "items": [
            {
              "sub": "a",
              "text": "Organise campaigns for environmental awareness"
            },
            {
              "sub": "b",
              "text": "Motivating local action for its upgrading, planting of trees, etc."
            },
            {
              "sub": "c",
              "text": "Reclamation of waste lands, promotion of social forestry and maintenance of open spaces"
            },
            {
              "sub": "d",
              "text": "Establishment and maintenance of nurseries, promotion of greenery"
            }
          ]
        },
        {
          "number": "iii",
          "title": "Small Scale Industries",
          "items": [
            {
              "sub": "a",
              "text": "Promotion of handicrafts"
            },
            {
              "sub": "b",
              "text": "Formulate and implement self-employment schemes in industrial sector"
            },
            {
              "sub": "c",
              "text": "Implementation of the entrepreneur development programmes"
            }
          ]
        },
        {
          "number": "iv",
          "title": "Housing",
          "items": [
            {
              "sub": "a",
              "text": "Identify the homeless, provision of house sites and houses, implementation of shelter rejuvenation programmes"
            },
            {
              "sub": "b",
              "text": "Mobilise fund necessary for housing"
            }
          ]
        },
        {
          "number": "v",
          "title": "Education and Culture",
          "items": [
            {
              "sub": "a",
              "text": "Run the pre-primary, primary, higher secondary and technical schools, vocational training centres, and implement literacy programmes"
            },
            {
              "sub": "b",
              "text": "Promote civic education, adult education, social education including family planning, environmental education and non formal education"
            },
            {
              "sub": "c",
              "text": "Promotion of cultural activities including music, physical education, sports and theatres and infrastructure therefor"
            },
            {
              "sub": "d",
              "text": "Advancement of science and technology in urban life"
            },
            {
              "sub": "e",
              "text": "Organization, establishment and maintenance of art galleries and botanical or zoological collections"
            },
            {
              "sub": "f",
              "text": "Maintenance of City Corporation office, and of all public monuments and places of historical, artistic and other importance"
            },
            {
              "sub": "g",
              "text": "Presentation of awards to persons of distinction, paying homage on death to persons of repute"
            },
            {
              "sub": "h",
              "text": "Holding and regulation of fairs, festivals, industrial and health exhibitions"
            }
          ]
        },
        {
          "number": "vi",
          "title": "Public Works",
          "items": [
            {
              "sub": "a",
              "text": "Construct and maintain the roads except National Highways, State Highways and major District roads within the City Corporation, and buildings for institutions including those transferred from Government"
            }
          ]
        },
        {
          "number": "vii",
          "title": "Public Health and Sanitation",
          "items": [
            {
              "sub": "a",
              "text": "Run dispensaries, primary and public health centers and hospitals under all systems of medicines, child welfare centers and mother care homes"
            },
            {
              "sub": "b",
              "text": "Organise remedial and other preventive measures against disease"
            },
            {
              "sub": "c",
              "text": "Implement family welfare programmes"
            },
            {
              "sub": "d",
              "text": "Organise mass inoculation campaigns for eradication of infectious diseases"
            },
            {
              "sub": "e",
              "text": "Reclamation of unhealthy localities, removal of noxious vegetation and abatement of all nuisances"
            },
            {
              "sub": "f",
              "text": "Maintenance of all public tanks and regulating the re-excavation, repair and up-keep of all tanks, wells and other sources of water-supply and provision for unfiltered water supply for non-domestic uses"
            },
            {
              "sub": "g",
              "text": "Public vaccination, prophylactic inoculations, vector control"
            },
            {
              "sub": "h",
              "text": "Maintenance of ambulance service"
            },
            {
              "sub": "i",
              "text": "Advancement of civic consciousness of public health and general welfare by organizing discourses, seminars and conferences"
            },
            {
              "sub": "j",
              "text": "Prevention of food adulteration and control of eating-houses"
            },
            {
              "sub": "k",
              "text": "Effective implementation of national and state strategies and programmes for prevention and control of diseases"
            }
          ]
        },
        {
          "number": "viii",
          "title": "Social Welfare",
          "items": [
            {
              "sub": "a",
              "text": "Run Anganwadis, and institutions for the welfare of persons with disability, urban poor among others"
            },
            {
              "sub": "b",
              "text": "Sanction and distribute pension to persons with disability, widows, urban poor, distribute unemployment wages, and implement Group Insurance Scheme to the poor"
            },
            {
              "sub": "c",
              "text": "Implementation of programmes for liberation and rehabilitation of scavengers and their families"
            },
            {
              "sub": "d",
              "text": "Campaigns for dissemination of information, vital for public welfare"
            },
            {
              "sub": "e",
              "text": "Securing or removal of dangerous buildings and places, obstructions and projections in or upon streets, bridges and other public places"
            }
          ]
        },
        {
          "number": "ix",
          "title": "Eradication of Poverty",
          "items": [
            {
              "sub": "a",
              "text": "Develop skills and implement self-employment and group employment schemes for the poor, especially for women"
            },
            {
              "sub": "b",
              "text": "Create community assets to get continuing benefit to the poor"
            }
          ]
        },
        {
          "number": "x",
          "title": "Development of Persons belonging to Scheduled Caste/Scheduled Tribe",
          "items": [
            {
              "sub": "a",
              "text": "Implementation of beneficiary-oriented schemes under Special Component Plan (SCP) and Tribal Sub Plan (TSP) and provide basic facilities in the residential centres and financial assistance for the Scheduled Caste/Scheduled Tribe"
            },
            {
              "sub": "b",
              "text": "Run nursery schools, vocational training centres for the Scheduled Caste/Scheduled Tribe"
            }
          ]
        },
        {
          "number": "xi",
          "title": "Public Distribution System",
          "items": [
            {
              "sub": "a",
              "text": "Examine complaints against public distribution system and find out and implement remedial measures"
            },
            {
              "sub": "b",
              "text": "Organise campaigns against offences relating to weights and measures"
            },
            {
              "sub": "c",
              "text": "General supervision of shops and other public distribution system and to provide guidance"
            }
          ]
        },
        {
          "number": "xii",
          "title": "Disaster Relief",
          "items": [
            {
              "sub": "a",
              "text": "Maintain relief centres and organise relief activities like provision to hospitals, dispensaries, asylums, rescue homes, maternity houses, and child welfare centres, crematorium, burial ground among other"
            }
          ]
        }
      ]
    }
  }
}